wagtail_content_audit/__init__.py
wagtail_content_audit/apps.py
wagtail_content_audit/utils.py
wagtail_content_audit/management/__init__.py
wagtail_content_audit/management/commands/__init__.py
wagtail_content_audit/management/commands/block_usage.py
wagtail_content_audit/management/commands/page_search.py
wagtail_content_audit/query/__init__.py
wagtail_content_audit/query/blockusage.py
wagtail_content_audit/query/pagesearch.py
wagtail_content_audit/tests/__init__.py
wagtail_content_audit/tests/settings.py
wagtail_content_audit/tests/test_management_commands_block_usage.py
wagtail_content_audit/tests/test_management_commands_page_search.py
wagtail_content_audit/tests/test_query_blockusage.py
wagtail_content_audit/tests/test_query_pagesearch.py
wagtail_content_audit/tests/test_utils.py
wagtail_content_audit/tests/urls.py
wagtail_content_audit/tests/testapp/__init__.py
wagtail_content_audit/tests/testapp/models.py
wagtail_content_audit/tests/testapp/migrations/0001_initial.py
wagtail_content_audit/tests/testapp/migrations/__init__.py
wagtail_content_audit-0.1.dist-info/LICENSE
wagtail_content_audit-0.1.dist-info/METADATA
wagtail_content_audit-0.1.dist-info/WHEEL
wagtail_content_audit-0.1.dist-info/top_level.txt
wagtail_content_audit-0.1.dist-info/RECORD
