Metadata-Version: 2.1
Name: wagtail-content-audit
Version: 0.1
Summary: Tools for performing content audits of Wagtail sites
Author-email: CFPB <tech@cfpb.gov>
License: CC0
Project-URL: Homepage, https://github.com/cfpb/wagtail-content-audit
Project-URL: Bug Reports, https://github.com/cfpb/wagtail-content-audit/issues
Project-URL: Source, https://github.com/cfpb/wagtail-content-audit
Classifier: Framework :: Django
Classifier: Framework :: Django :: 4.2
Classifier: Framework :: Wagtail
Classifier: Framework :: Wagtail :: 5
Classifier: License :: CC0 1.0 Universal (CC0 1.0) Public Domain Dedication
Classifier: License :: Public Domain
Classifier: Programming Language :: Python
Classifier: Programming Language :: Python :: 3
Requires-Python: >=3.8
License-File: LICENSE
Requires-Dist: django >=4.2
Requires-Dist: wagtail >=5.2
Requires-Dist: queryish
Provides-Extra: testing
Requires-Dist: coverage[toml] ; extra == 'testing'
